justrpa/__init__.py
justrpa/errors.py
justrpa/browser/__init__.py
justrpa/browser/chrome.py
justrpa/browser/firefox.py
justrpa/browser/report.py
justrpa/browser/selenium.py
justrpa/browser/task.py
justrpa/task/__init__.py
justrpa/task/executer.py
justrpa/task/handler.py
justrpa/utils/__init__.py
justrpa/utils/config.py
justrpa/utils/file.py
justrpa/utils/site.py
justrpa/utils/time.py
justrpa-0.1.3.dist-info/METADATA
justrpa-0.1.3.dist-info/WHEEL
justrpa-0.1.3.dist-info/top_level.txt
justrpa-0.1.3.dist-info/RECORD
