Metadata-Version: 2.1
Name: justrpa
Version: 0.1.3
Summary: Just RPA Common Library
Home-page: https://justrpa.com/
Author: loop
Author-email: jing.yan.cn@gmail.com
License: MIT
Platform: UNKNOWN
Classifier: Intended Audience :: Developers
Classifier: License :: OSI Approved :: MIT License
Classifier: Programming Language :: Python
Classifier: Programming Language :: Python :: 3
Classifier: Programming Language :: Python :: 3.6
Classifier: Programming Language :: Python :: 3.7
Classifier: Programming Language :: Python :: 3.8
Classifier: Programming Language :: Python :: 3.9
Classifier: Operating System :: OS Independent
Requires-Dist: rpaframework (==9.5.0)
Requires-Dist: pandas (==1.2.5)
Requires-Dist: xlsxwriter (==3.0.3)
Requires-Dist: psutil (==5.9.1)
